advanced_descriptors/__init__.py
advanced_descriptors/_version.py
advanced_descriptors/advanced_property.py
advanced_descriptors/log_on_access.py
advanced_descriptors/py.typed
advanced_descriptors/separate_class_method.py
advanced_descriptors-4.0.3.dist-info/LICENSE
advanced_descriptors-4.0.3.dist-info/METADATA
advanced_descriptors-4.0.3.dist-info/WHEEL
advanced_descriptors-4.0.3.dist-info/top_level.txt
advanced_descriptors-4.0.3.dist-info/RECORD
