Metadata-Version: 2.1
Name: advanced-descriptors
Version: 4.0.3
Summary: Advanced descriptors for special cases.
Author-email: Alexey Stepanov <penguinolog@gmail.com>
Maintainer-email: Alexey Stepanov <penguinolog@gmail.com>, Antonio Esposito <esposito.cloud@gmail.com>, Dennis Dmitriev <dis-xcom@gmail.com>
License: Apache License, Version 2.0
Project-URL: Bug Tracker, https://github.com/python-useful-helpers/advanced-descriptors/issues
Project-URL: Documentation, https://advanced-descriptors.readthedocs.io/
Keywords: descriptor,property,classmethod,development
Classifier: Development Status :: 5 - Production/Stable
Classifier: Intended Audience :: Developers
Classifier: Topic :: Software Development :: Libraries :: Python Modules
Classifier: License :: OSI Approved :: Apache Software License
Classifier: Programming Language :: Python :: 3
Classifier: Programming Language :: Python :: 3 :: Only
Classifier: Programming Language :: Python :: 3.7
Classifier: Programming Language :: Python :: 3.8
Classifier: Programming Language :: Python :: 3.9
Classifier: Programming Language :: Python :: 3.10
Classifier: Programming Language :: Python :: 3.11
Classifier: Programming Language :: Python :: Implementation :: CPython
Classifier: Programming Language :: Python :: Implementation :: PyPy
Requires-Python: >=3.7.0
License-File: LICENSE
